qmetagpt/__init__.py
qmetagpt/evaluation_engine/__init__.py
qmetagpt/evaluation_engine/quantum_evaluator.py
qmetagpt/evaluation_engine/result_formatter.py
qmetagpt/frontend_interface/__init__.py
qmetagpt/frontend_interface/app.py
qmetagpt/frontend_interface/routes.py
qmetagpt/licensing/__init__.py
qmetagpt/licensing/license_enforcer.py
qmetagpt/llm_paper_parser/__init__.py
qmetagpt/llm_paper_parser/arxiv_parser.py
qmetagpt/llm_paper_parser/llm_integration.py
qmetagpt/llm_paper_parser/summary_extractor.py
qmetagpt/optimizer_engine/__init__.py
qmetagpt/optimizer_engine/hybrid_optimizer.py
qmetagpt/optimizer_engine/optimizer_plugins.py
qmetagpt/quantum_algorithm_generator/__init__.py
qmetagpt/quantum_algorithm_generator/agent_registry.py
qmetagpt/quantum_algorithm_generator/ansatz_library.py
qmetagpt/quantum_algorithm_generator/base_rl_agent.py
qmetagpt/quantum_algorithm_generator/circuit_enviroment.py
qmetagpt/quantum_algorithm_generator/reward_calculator.py
qmetagpt/report_generator/__init__.py
qmetagpt/report_generator/latex_templates.py
qmetagpt/report_generator/report_builder.py
qmetagpt/report_generator/visualization.py
qmetagpt/security_licensing/__init__.py
qmetagpt/security_licensing/cli_license.py
qmetagpt/security_licensing/license_manager.py
qmetagpt/task_synthesizer/__init__.py
qmetagpt/task_synthesizer/synthesizer.py
qmetagpt/utils/__init__.py
qmetagpt/utils/error_handling.py
qmetagpt/utils/logger.py
quantummetagpt-1.0.0.dist-info/licenses/LICENSE
tests/__init__.py
tests/test_evaluation.py
tests/test_generator.py
tests/test_llm_parser.py
tests/test_optimizer.py
tests/test_quantum_generator.py
quantummetagpt-1.0.0.dist-info/METADATA
quantummetagpt-1.0.0.dist-info/WHEEL
quantummetagpt-1.0.0.dist-info/top_level.txt
quantummetagpt-1.0.0.dist-info/RECORD
