Metadata-Version: 2.4
Name: QuantumMetaGPT
Version: 1.0.0
Summary: Autonomous quantum AI research agent
Author: Quantum Research Team
Project-URL: Homepage, https://github.com/yourusername/QuantumMetaGPT
Project-URL: Documentation, https://quantummetagpt.readthedocs.io
Project-URL: Repository, https://github.com/yourusername/QuantumMetaGPT
Classifier: Development Status :: 3 - Alpha
Classifier: Intended Audience :: Science/Research
Classifier: License :: Other/Proprietary License
Classifier: Programming Language :: Python :: 3.10
Classifier: Topic :: Scientific/Engineering :: Artificial Intelligence
Requires-Python: >=3.8
License-File: LICENSE
Requires-Dist: qiskit>=0.44
Requires-Dist: qiskit-ibmq-provider
Requires-Dist: stable-baselines3>=2.0
Requires-Dist: gym>=0.26
Requires-Dist: arxiv>=1.4
Requires-Dist: openai>=0.27
Requires-Dist: transformers>=4.30
Requires-Dist: torch>=2.0
Requires-Dist: matplotlib>=3.7
Requires-Dist: pylatex>=1.4
Requires-Dist: cryptography>=41.0
Requires-Dist: fastapi>=0.95
Requires-Dist: uvicorn>=0.22
Requires-Dist: python-dotenv>=1.0
Requires-Dist: jinja2>=3.1
Requires-Dist: pytest>=7.0
Requires-Dist: quantummeta-license
Dynamic: author
Dynamic: license-file
Dynamic: requires-python
